toliman/__init__.py
toliman/overview.md
toliman/toliman.py
toliman-0.0.2.dist-info/WHEEL
toliman-0.0.2.dist-info/LICENSE.md
toliman-0.0.2.dist-info/METADATA
toliman-0.0.2.dist-info/RECORD
