Metadata-Version: 2.1
Name: toliman
Version: 0.0.2
Summary: A differential model of TOLIMAN telescope.
Author: Jordan Dennis
Author-email: jdenn105@gmail.com
Requires-Python: >=3.10,<3.11
Classifier: Programming Language :: Python :: 3
Classifier: Programming Language :: Python :: 3.10
Requires-Dist: astroquery (>=0.4.6,<0.5.0)
Requires-Dist: dLux (>=0.9)
Requires-Dist: jax (>=0.4.1)
Requires-Dist: opt-einsum (>=3.3.0,<4.0.0)
Requires-Dist: pysynphot (>=2.0.0)
